{"files":{"packages/shared/dist/types/order.d.ts.map":{"size":462,"mtime_nanos":1780247664245008826,"mode":420,"is_dir":false},"packages/shared/dist/types/order.js.map":{"size":111,"mtime_nanos":1780247664243905827,"mode":420,"is_dir":false},"packages/shared/dist/types/index.d.ts":{"size":139,"mtime_nanos":1780247664247334199,"mode":420,"is_dir":false},"packages/shared/dist/types/order.js":{"size":44,"mtime_nanos":1780247664243961411,"mode":420,"is_dir":false},"packages/shared/dist/types/product.d.ts":{"size":185,"mtime_nanos":1780247664242664620,"mode":420,"is_dir":false},"packages/shared/dist/types/cart.d.ts.map":{"size":349,"mtime_nanos":1780247664243621453,"mode":420,"is_dir":false},"packages/shared/dist/types/cart.js":{"size":43,"mtime_nanos":1780247664243029453,"mode":420,"is_dir":false},"packages/shared/dist/index.js.map":{"size":102,"mtime_nanos":1780247664247562448,"mode":420,"is_dir":false},"packages/shared/dist/types/discount.d.ts":{"size":228,"mtime_nanos":1780247664246414408,"mode":420,"is_dir":false},"packages/shared/dist/types/discount.js.map":{"size":117,"mtime_nanos":1780247664245722159,"mode":420,"is_dir":false},"packages/shared/dist/types/discount.js":{"size":47,"mtime_nanos":1780247664245844075,"mode":420,"is_dir":false},"packages/shared/dist/index.js":{"size":44,"mtime_nanos":1780247664247624615,"mode":420,"is_dir":false},"packages/shared/dist/types/discount.d.ts.map":{"size":308,"mtime_nanos":1780247664246186742,"mode":420,"is_dir":false},"packages/shared/dist":{"size":0,"mtime_nanos":0,"mode":0,"is_dir":true},"packages/shared/.turbo/turbo-build.log":{"size":116,"mtime_nanos":1780247664257732687,"mode":420,"is_dir":false},"packages/shared/dist/types":{"size":0,"mtime_nanos":0,"mode":0,"is_dir":true},"packages/shared/dist/types/cart.js.map":{"size":109,"mtime_nanos":1780247664242964995,"mode":420,"is_dir":false},"packages/shared/dist/types/index.js":{"size":137,"mtime_nanos":1780247664246986407,"mode":420,"is_dir":false},"packages/shared/dist/types/order.d.ts":{"size":357,"mtime_nanos":1780247664245163409,"mode":420,"is_dir":false},"packages/shared/dist/types/product.d.ts.map":{"size":294,"mtime_nanos":1780247664242589912,"mode":420,"is_dir":false},"packages/shared/dist/types/product.js":{"size":46,"mtime_nanos":1780247664240733914,"mode":420,"is_dir":false},"packages/shared/dist/types/index.d.ts.map":{"size":195,"mtime_nanos":1780247664247214365,"mode":420,"is_dir":false},"packages/shared/dist/types/product.js.map":{"size":115,"mtime_nanos":1780247664240623164,"mode":420,"is_dir":false},"packages/shared/dist/index.d.ts.map":{"size":517,"mtime_nanos":1780247664248125114,"mode":420,"is_dir":false},"packages/shared/dist/types/index.js.map":{"size":193,"mtime_nanos":1780247664246901991,"mode":420,"is_dir":false},"packages/shared/dist/types/cart.d.ts":{"size":252,"mtime_nanos":1780247664243671786,"mode":420,"is_dir":false},"packages/shared/dist/index.d.ts":{"size":400,"mtime_nanos":1780247664248173323,"mode":420,"is_dir":false}},"order":["packages/shared/.turbo/turbo-build.log","packages/shared/dist","packages/shared/dist/index.d.ts","packages/shared/dist/index.d.ts.map","packages/shared/dist/index.js","packages/shared/dist/index.js.map","packages/shared/dist/types","packages/shared/dist/types/cart.d.ts","packages/shared/dist/types/cart.d.ts.map","packages/shared/dist/types/cart.js","packages/shared/dist/types/cart.js.map","packages/shared/dist/types/discount.d.ts","packages/shared/dist/types/discount.d.ts.map","packages/shared/dist/types/discount.js","packages/shared/dist/types/discount.js.map","packages/shared/dist/types/index.d.ts","packages/shared/dist/types/index.d.ts.map","packages/shared/dist/types/index.js","packages/shared/dist/types/index.js.map","packages/shared/dist/types/order.d.ts","packages/shared/dist/types/order.d.ts.map","packages/shared/dist/types/order.js","packages/shared/dist/types/order.js.map","packages/shared/dist/types/product.d.ts","packages/shared/dist/types/product.d.ts.map","packages/shared/dist/types/product.js","packages/shared/dist/types/product.js.map"]}